cgli/__init__.py
cgli/cgli.py
cgli-0.0.4.dist-info/LICENSE
cgli-0.0.4.dist-info/METADATA
cgli-0.0.4.dist-info/WHEEL
cgli-0.0.4.dist-info/top_level.txt
cgli-0.0.4.dist-info/RECORD
